cs/seq.py
cs_seq-20251231.1.dist-info/WHEEL
cs_seq-20251231.1.dist-info/METADATA
cs_seq-20251231.1.dist-info/RECORD
